ainstorage/__init__.py
ainstorage/auth.py
ainstorage/encrypt_manager.py
ainstorage/transfer.py
ainstorage/wallet.py
ainstorage/write_ain.py
ainstorage/cli_tools/__init__.py
ainstorage/cli_tools/main.py
ainstorage/cli_tools/auth_cli/__init__.py
ainstorage/cli_tools/auth_cli/commands.py
ainstorage/cli_tools/transfer_cli/__init__.py
ainstorage/cli_tools/transfer_cli/commands.py
ainstorage-0.0.6.dist-info/LICENSE
ainstorage-0.0.6.dist-info/METADATA
ainstorage-0.0.6.dist-info/WHEEL
ainstorage-0.0.6.dist-info/entry_points.txt
ainstorage-0.0.6.dist-info/top_level.txt
ainstorage-0.0.6.dist-info/RECORD
